routemin
test
