Metadata-Version: 2.1
Name: routemin
Version: 0.1.2
Summary: 最短経路探索ライブラリ
Author: elmomuds
Author-email: s2122088@stu.musashino-u.ac.jp
Classifier: Programming Language :: Python :: 3
Classifier: License :: OSI Approved :: MIT License
Classifier: Operating System :: OS Independent
Requires-Python: >=3.6
License-File: LICENSE
Requires-Dist: networkx
